Linkmaths_quarto/__init__.py
Linkmaths_quarto/link_color.py
Linkmaths_quarto/data/X_test.pkl
Linkmaths_quarto/data/X_train.pkl
Linkmaths_quarto/data/sample_submission.csv
Linkmaths_quarto/data/sample_submission_lgb2.csv
Linkmaths_quarto/data/sample_submission_lgb3.csv
Linkmaths_quarto/data/sample_submission_lgb4.csv
Linkmaths_quarto/data/sample_submission_lr.csv
Linkmaths_quarto/data/sample_submission_mlp.csv
Linkmaths_quarto/data/sample_submission_rf.csv
Linkmaths_quarto/data/target_test.pkl
Linkmaths_quarto/data/target_train.pkl
Linkmaths_quarto/data/test.csv
Linkmaths_quarto/data/test_dm.pkl
Linkmaths_quarto/data/train.csv
Linkmaths_quarto/data/train_dm.pkl
Linkmaths_quarto/data/y_test.pkl
Linkmaths_quarto/data/y_train.pkl
Linkmaths_quarto/documents/logo-linkpact.png
Linkmaths_quarto/documents/rendu_html.html
Linkmaths_quarto/documents/rendu_html.qmd
Linkmaths_quarto/documents/rendu_pdf.html
Linkmaths_quarto/documents/rendu_pdf.log
Linkmaths_quarto/documents/rendu_pdf.qmd
Linkmaths_quarto/documents/rendu_pdf.tex
Linkmaths_quarto/modele/clf_lgb.pkl
Linkmaths_quarto/modele/clf_lgb_07993.pkl
Linkmaths_quarto/modele/clf_rf.pkl
Linkmaths_quarto/modele/clf_rl.pkl
Linkmaths_quarto/modele/grid_best_estimator.pkl
Linkmaths_quarto/modele/mlp.pkl
Linkmaths_quarto/presentation/logo-linkpact.png
Linkmaths_quarto/presentation/rendu_beamer.pdf
Linkmaths_quarto/presentation/rendu_beamer.qmd
Linkmaths_quarto/website/.gitignore
Linkmaths_quarto/website/DataExploratyAnalysis_Nguy_Ref_V1.ipynb
Linkmaths_quarto/website/Lgbm_Nguy_Ref_V1.ipynb
Linkmaths_quarto/website/LogisticRegression_Nguy_Ref_V1.ipynb
Linkmaths_quarto/website/_quarto.yml
Linkmaths_quarto/website/intro.qmd
Linkmaths_quarto/website/logo-linkpact.png
Linkmaths_quarto/website/style_website.css
Linkmaths_quarto/website/theme.scss
linkmaths_quarto-1.1.dist-info/LICENSE
linkmaths_quarto-1.1.dist-info/METADATA
linkmaths_quarto-1.1.dist-info/WHEEL
linkmaths_quarto-1.1.dist-info/top_level.txt
linkmaths_quarto-1.1.dist-info/RECORD
