Metadata-Version: 2.1
Name: linkmaths-quarto
Version: 1.1
Summary: templates quarto au format linkpact
Home-page: https://github.com/GuyNYAMSI/linkmaths_quarto
Author: guy nyamsi
Author-email: nyamsguy@gmail.com
Classifier: Programming Language :: Python :: 3.9
Classifier: License :: OSI Approved :: MIT License
Classifier: Operating System :: OS Independent
Requires-Python: >=3.9
License-File: LICENSE
